{"settlements":[{"month":"JAN 20","open":"1.11525","high":"1.11650B","low":"1.11290A","last":"1.11425A","change":"+.00055","settle":"1.11445","volume":"693","openInterest":"1,837"},{"month":"FEB 20","open":"1.11770","high":"1.11885","low":"1.11520","last":"1.11670A","change":"+.00055","settle":"1.11690","volume":"848","openInterest":"2,048"},{"month":"MAR 20","open":"1.11835","high":"1.12095","low":"1.11725","last":"1.11855A","change":"+.00055","settle":"1.11885","volume":"149,357","openInterest":"532,013"},{"month":"APR 20","open":"1.12070","high":"1.12250B","low":"1.11965A","last":"1.12065A","change":"+.00055","settle":"1.12085","volume":"65","openInterest":"141"},{"month":"JUN 20","open":"1.12600","high":"1.12730B","low":"1.12360A","last":"1.12480B","change":"+.00055","settle":"1.12520","volume":"215","openInterest":"2,452"},{"month":"SEP 20","open":"1.13130","high":"1.13300B","low":"1.13010A","last":"1.13145A","change":"+.00060","settle":"1.13145","volume":"3","openInterest":"688"},{"month":"DEC 20","open":"-","high":"1.13830B","low":"-","last":"1.13760A","change":"+.00040","settle":"1.13750","volume":"1","openInterest":"662"},{"month":"MAR 21","open":"1.14400","high":"1.14410B","low":"1.14400","last":"1.14410B","change":"+.00035","settle":"1.14350","volume":"6","openInterest":"2"},{"month":"JUN 21","open":"-","high":"-","low":"-","last":"-","change":"+.00020","settle":"1.14945","volume":"0","openInterest":"0"},{"month":"SEP 21","open":"-","high":"-","low":"-","last":"-","change":"+.00010","settle":"1.15540","volume":"0","openInterest":"1"},{"month":"DEC 21","open":"-","high":"-","low":"-","last":"-","change":"+.00005","settle":"1.16140","volume":"0","openInterest":"0"},{"month":"MAR 22","open":"-","high":"-","low":"-","last":"-","change":"-.00010","settle":"1.16730","volume":"0","openInterest":"0"},{"month":"JUN 22","open":"-","high":"-","low":"-","last":"-","change":"-.00020","settle":"1.17325","volume":"0","openInterest":"0"},{"month":"SEP 22","open":"-","high":"-","low":"-","last":"-","change":"-.00030","settle":"1.17965","volume":"0","openInterest":"0"},{"month":"DEC 22","open":"-","high":"-","low":"-","last":"-","change":"-.00040","settle":"1.18560","volume":"0","openInterest":"0"},{"month":"MAR 23","open":"-","high":"-","low":"-","last":"-","change":"-.00055","settle":"1.19105","volume":"0","openInterest":"0"},{"month":"JUN 23","open":"-","high":"-","low":"-","last":"-","change":"-.00065","settle":"1.19745","volume":"0","openInterest":"0"},{"month":"SEP 23","open":"-","high":"-","low":"-","last":"-","change":"-.00075","settle":"1.20340","volume":"0","openInterest":"0"},{"month":"DEC 23","open":"-","high":"-","low":"-","last":"-","change":"-.00090","settle":"1.20930","volume":"0","openInterest":"0"},{"month":"MAR 24","open":"-","high":"-","low":"-","last":"-","change":"-.00100","settle":"1.21525","volume":"0","openInterest":"0"},{"month":"JUN 24","open":"-","high":"-","low":"-","last":"-","change":"-.00110","settle":"1.22120","volume":"0","openInterest":"0"},{"month":"SEP 24","open":"-","high":"-","low":"-","last":"-","change":"-.00120","settle":"1.22710","volume":"0","openInterest":"0"},{"month":"DEC 24","open":"-","high":"-","low":"-","last":"-","change":"-.00130","settle":"1.23305","volume":"0","openInterest":"0"},{"month":"Total","open":"","high":"","low":"","last":"","change":"","settle":"","volume":"151,188","openInterest":"539,844"}],"updateTime":"Friday, 20 Dec 2019 06:00 PM","dsHeader":"Euro FX Future","reportType":"Final","tradeDate":"12/19/2019","empty":false}